dihlibs/SQLCipherDialect.py
dihlibs/__init__.py
dihlibs/command.py
dihlibs/cron_logger.py
dihlibs/database.py
dihlibs/db.py
dihlibs/drive.py
dihlibs/evaluator.py
dihlibs/fs_secret.py
dihlibs/functions.py
dihlibs/graph.py
dihlibs/jsonq.py
dihlibs/matview.py
dihlibs/node.py
dihlibs/superset_api.py
dihlibs/data/describe_table.sql
dihlibs/data/df_update_table.sql
dihlibs/data/bash/script.sh
dihlibs/data/dhis_templates/category_options.json
dihlibs/data/dhis_templates/data_element.json
dihlibs/data/dhis_templates/data_set.json
dihlibs/data/docker/backend.zip
dihlibs/data/docker/cronies.zip
dihlibs/dhis/__init__.py
dihlibs/dhis/configuration.py
dihlibs/dhis/fill_new_element.py
dihlibs/dhis/main.py
dihlibs/dhis/meta.py
dihlibs-0.0.93.dist-info/METADATA
dihlibs-0.0.93.dist-info/WHEEL
dihlibs-0.0.93.dist-info/entry_points.txt
dihlibs-0.0.93.dist-info/top_level.txt
dihlibs-0.0.93.dist-info/RECORD
