Metadata-Version: 2.1
Name: dihlibs
Version: 0.0.93
Summary: A helper package for data integrations
Home-page: https://github.com/nKataraia/dihlibs
Author: Nitu
Author-email: nkataraia@d-tree.org
Classifier: Programming Language :: Python :: 3
Classifier: License :: OSI Approved :: MIT License
Classifier: Operating System :: OS Independent
Requires-Python: >=3.6
Requires-Dist: asyncio
Requires-Dist: requests
Requires-Dist: pandas
Requires-Dist: openpyxl
Requires-Dist: SQLAlchemy
Requires-Dist: psycopg2-binary
Requires-Dist: pyjwt
Requires-Dist: google-api-python-client
Requires-Dist: google-auth-oauthlib
Requires-Dist: google-auth
Requires-Dist: aiohttp
Requires-Dist: pyyaml
Requires-Dist: fuzzywuzzy
Requires-Dist: setuptools
Requires-Dist: python-Levenshtein
Requires-Dist: cryptography
